linode_mcp/__init__.py
linode_mcp/server.py
linode_mcp/tools/__init__.py
linode_mcp/tools/linode_tools.py
mcp_linode-0.1.0.dist-info/LICENSE
mcp_linode-0.1.0.dist-info/METADATA
mcp_linode-0.1.0.dist-info/WHEEL
mcp_linode-0.1.0.dist-info/entry_points.txt
mcp_linode-0.1.0.dist-info/top_level.txt
mcp_linode-0.1.0.dist-info/RECORD
