Metadata-Version: 2.2
Name: mcp-linode
Version: 0.1.0
Summary: Model Context Protocol server for Linode API
Author: Khaja Omer
License: MIT
Project-URL: Homepage, https://github.com/komer3/linode-mcp
Project-URL: Bug Tracker, https://github.com/komer3/linode-mcp/issues
Project-URL: Documentation, https://github.com/komer3/linode-mcp#readme
Classifier: Programming Language :: Python :: 3
Classifier: Programming Language :: Python :: 3.10
Classifier: License :: OSI Approved :: MIT License
Classifier: Operating System :: OS Independent
Classifier: Development Status :: 4 - Beta
Classifier: Intended Audience :: Developers
Classifier: Topic :: Software Development :: Libraries :: Python Modules
Requires-Python: >=3.13
License-File: LICENSE
Requires-Dist: linode-api4==5.27.0
Requires-Dist: pydantic<3.0.0,>=2.10.6
Requires-Dist: python-dotenv==1.0.1
Requires-Dist: mcp>=1.3.0
Dynamic: requires-python
